jupyter_translation/__init__.py
jupyter_translation/__main__.py
jupyter_translation/cli.py
jupyter_translation/errors.py
jupyter_translation/translate.py
jupyter_translation-0.1.3.dist-info/METADATA
jupyter_translation-0.1.3.dist-info/WHEEL
jupyter_translation-0.1.3.dist-info/entry_points.txt
jupyter_translation-0.1.3.dist-info/licenses/LICENSE
jupyter_translation-0.1.3.dist-info/RECORD
