Metadata-Version: 2.4
Name: jupyter-translation
Version: 0.1.3
Summary: Translate Jupyter Notebooks using Google Translate
Project-URL: source, https://github.com/numgrade/jupyter_translation
Project-URL: tracker, https://github.com/numgrade/jupyter_translation/issues
Author-email: numgrade <num@numgrade.com>
License-File: LICENSE
Requires-Python: >=3.9
Requires-Dist: googletrans>=4.0.2
Requires-Dist: nbformat>=5.10.4
Requires-Dist: typer>=0.15.1
